# 作业一

## 1（可选）、自己写一个简单的 Hello.java，里面需要涉及基本类型，四则运行，if 和for，然后自己分析一下对应的字节码，有问题群里讨论。

Java源代码demo如下：

```java
package com.raw;

/**
 * @author raw
 * @date 2021/1/9
 */
public class Hello {
    public static void main(String[] args) {
        int a = 1;
        double b = 2.0d;

        double sum = a + b;
        double sub = b - a;
        double mul = a * b;
        double div = b / a;

        if (b / a > 0) {
            System.out.println("b/a>0");
        }

        for (int i = 0; i < 10; i++) {
            a++;
        }
    }
}

```

字节码分析如下：

```
Classfile /D:/Intellij IDEA/Learn/practice/src/com/raw/Hello.class
  Last modified 2021-1-9; size 799 bytes
  MD5 checksum cbc0a308388da440d0ae319f70650179
  Compiled from "Hello.java"
public class com.raw.Hello
  // JDK1.8版本号
  minor version: 0
  major version: 52
  flags: ACC_PUBLIC, ACC_SUPER
Constant pool:
   // 方法引用
   #1 = Methodref          #8.#33         // java/lang/Object."<init>":()V
   #2 = Double             2.0d
   // 字段引用
   #4 = Fieldref           #34.#35        // java/lang/System.out:Ljava/io/PrintStream;
   #5 = String             #36            // b/a>0
   #6 = Methodref          #37.#38        // java/io/PrintStream.println:(Ljava/lang/String;)V
   // 类全限定名
   #7 = Class              #39            // com/raw/Hello
   #8 = Class              #40            // java/lang/Object
   #9 = Utf8               <init>
  #10 = Utf8               ()V
  #11 = Utf8               Code
  #12 = Utf8               LineNumberTable
  #13 = Utf8               LocalVariableTable
  #14 = Utf8               this
  #15 = Utf8               Lcom/raw/Hello;
  #16 = Utf8               main
  // ()表示参数信息，[表示数组，L表示对象
  #17 = Utf8               ([Ljava/lang/String;)V
  #18 = Utf8               i
  #19 = Utf8               I
  #20 = Utf8               args
  #21 = Utf8               [Ljava/lang/String;
  #22 = Utf8               a
  #23 = Utf8               b
  #24 = Utf8               D
  #25 = Utf8               sum
  #26 = Utf8               sub
  #27 = Utf8               mul
  #28 = Utf8               div
  #29 = Utf8               StackMapTable
  #30 = Class              #21            // "[Ljava/lang/String;"
  #31 = Utf8               SourceFile
  #32 = Utf8               Hello.java
  #33 = NameAndType        #9:#10         // "<init>":()V
  #34 = Class              #41            // java/lang/System
  #35 = NameAndType        #42:#43        // out:Ljava/io/PrintStream;
  #36 = Utf8               b/a>0
  #37 = Class              #44            // java/io/PrintStream
  #38 = NameAndType        #45:#46        // println:(Ljava/lang/String;)V
  #39 = Utf8               com/raw/Hello
  #40 = Utf8               java/lang/Object
  #41 = Utf8               java/lang/System
  #42 = Utf8               out
  #43 = Utf8               Ljava/io/PrintStream;
  #44 = Utf8               java/io/PrintStream
  #45 = Utf8               println
  #46 = Utf8               (Ljava/lang/String;)V
{
  public com.raw.Hello();
    descriptor: ()V
    flags: ACC_PUBLIC
    Code:
      stack=1, locals=1, args_size=1
      // String这个Object类型的初始化
         0: aload_0
         1: invokespecial #1                  // Method java/lang/Object."<init>":()V
         4: return
      LineNumberTable:
        line 7: 0
      LocalVariableTable:
        Start  Length  Slot  Name   Signature
            0       5     0  this   Lcom/raw/Hello;

  public static void main(java.lang.String[]);
    descriptor: ([Ljava/lang/String;)V
    flags: ACC_PUBLIC, ACC_STATIC
    Code:
      stack=4, locals=13, args_size=1
         // int类型的常量1压栈
         0: iconst_1
         // int类型数值存入本地变量表第二个槽位
         1: istore_1
         // 将long或double型常量值从常量池中取出压栈
         2: ldc2_w        #2                  // double 2.0d
         // double类型数值存入本地变量表第三和四个槽位
         5: dstore_2
         // 将本地变量表第二个槽位的值加载到栈中
         6: iload_1
         // int类型转double类型
         7: i2d
         8: dload_2
         9: dadd
        10: dstore        4
        12: dload_2
        13: iload_1
        14: i2d
        15: dsub
        16: dstore        6
        18: iload_1
        19: i2d
        20: dload_2
        21: dmul
        22: dstore        8
        24: dload_2
        25: iload_1
        26: i2d
        27: ddiv
        28: dstore        10
        30: dload_2
        31: iload_1
        32: i2d
        33: ddiv
        // 将double类型0压栈
        34: dconst_0
        // 比较栈顶两double型数值大小，并将结果（1，0，-1）压入栈顶；当其中一个数值为NaN时，将-1压入栈顶
        35: dcmpl
        // 当栈顶int型数值小于等于0时跳转
        36: ifle          47
        // 获取指定类的静态域，并将其值压栈
        39: getstatic     #4                  // Field java/lang/System.out:Ljava/io/PrintStream;
        // 将int, float或String型常量值从常量池中取出压栈
        42: ldc           #5                  // String b/a>0
        // 调用实例方法
        44: invokevirtual #6                  // Method java/io/PrintStream.println:(Ljava/lang/String;)V
        47: iconst_0
        48: istore        12
        50: iload         12
        // 将单字节的常量值(-128~127)推送至栈顶
        52: bipush        10
        // 比较栈顶两int型数值大小，当结果大于等于0时跳转
        54: if_icmpge     66
        57: iinc          1, 1
        60: iinc          12, 1
        63: goto          50
        66: return
      LineNumberTable:
        line 9: 0
        line 10: 2
        line 12: 6
        line 13: 12
        line 14: 18
        line 15: 24
        line 17: 30
        line 18: 39
        line 21: 47
        line 22: 57
        line 21: 60
        line 24: 66
      LocalVariableTable:
        Start  Length  Slot  Name   Signature
           50      16    12     i   I
            0      67     0  args   [Ljava/lang/String;
            2      65     1     a   I
            6      61     2     b   D
           12      55     4   sum   D
           18      49     6   sub   D
           24      43     8   mul   D
           30      37    10   div   D
      StackMapTable: number_of_entries = 3
        frame_type = 255 /* full_frame */
          offset_delta = 47
          locals = [ class "[Ljava/lang/String;", int, double, double, double, double, double ]
          stack = []
        frame_type = 252 /* append */
          offset_delta = 2
          locals = [ int ]
        frame_type = 250 /* chop */
          offset_delta = 15
}
SourceFile: "Hello.java"
```

